permadict.py
permadict-1.0.1.dist-info/DESCRIPTION.rst
permadict-1.0.1.dist-info/METADATA
permadict-1.0.1.dist-info/RECORD
permadict-1.0.1.dist-info/WHEEL
permadict-1.0.1.dist-info/metadata.json
permadict-1.0.1.dist-info/top_level.txt
