Metadata-Version: 2.0
Name: permadict
Version: 1.0.1
Summary: A trivial, persistent, dictionary-like object, backed by SQLite.
Home-page: https://github.com/mivade/permadict
Author: Michael V. DePalatis
Author-email: mike@depalatis.net
License: Unlicense
Platform: UNKNOWN
Classifier: Development Status :: 5 - Production/Stable
Classifier: Intended Audience :: Developers
Classifier: Intended Audience :: Science/Research
Classifier: License :: Public Domain
Classifier: Programming Language :: Python
Classifier: Programming Language :: Python :: 2
Classifier: Programming Language :: Python :: 3
Classifier: Topic :: Database
